mpex/__init__.py
mpex/main.py
tests/__init__.py
tests/test_main.py
mpex-0.1.2.dist-info/METADATA
mpex-0.1.2.dist-info/WHEEL
mpex-0.1.2.dist-info/top_level.txt
mpex-0.1.2.dist-info/RECORD
